dcar/__init__.py
dcar/address.py
dcar/auth.py
dcar/bus.py
dcar/const.py
dcar/errors.py
dcar/introspection.py
dcar/marshal.py
dcar/message.py
dcar/raw.py
dcar/remote.py
dcar/router.py
dcar/signature.py
dcar/transports.py
dcar/validate.py
dcar-0.3.0.dist-info/LICENSE.txt
dcar-0.3.0.dist-info/METADATA
dcar-0.3.0.dist-info/WHEEL
dcar-0.3.0.dist-info/top_level.txt
dcar-0.3.0.dist-info/RECORD
