Metadata-Version: 2.1
Name: dcar
Version: 0.3.0
Summary: Low level, pure Python D-Bus implementation for message bus clients.
Home-page: https://andreas19.github.io/dcar/
Author: Andreas Suhre
Author-email: andreas19@posteo.eu
License: BSD-3-Clause
Project-URL: Source code, https://github.com/andreas19/dcar/
Keywords: d-bus,dbus,message bus client
Platform: UNKNOWN
Classifier: Development Status :: 4 - Beta
Classifier: License :: OSI Approved :: BSD License
Classifier: Programming Language :: Python :: 3
Classifier: Programming Language :: Python :: 3.7
Classifier: Programming Language :: Python :: 3.8
Classifier: Intended Audience :: Developers
Classifier: Topic :: Software Development :: Libraries
Requires-Python: >=3.7
